odoo/addons/contract_api_somconnexio/CHANGELOG.md
odoo/addons/contract_api_somconnexio/README.md
odoo/addons/contract_api_somconnexio/__init__.py
odoo/addons/contract_api_somconnexio/__manifest__.py
odoo/addons/contract_api_somconnexio/migrations/16.0.1.0.6/post-migrate-fix-contract-recurrence.py
odoo/addons/contract_api_somconnexio/models/__init__.py
odoo/addons/contract_api_somconnexio/models/contract.py
odoo/addons/contract_api_somconnexio/services/__init__.py
odoo/addons/contract_api_somconnexio/services/contract_change_tariff_process.py
odoo/addons/contract_api_somconnexio/services/contract_change_tariff_service.py
odoo/addons/contract_api_somconnexio/services/contract_contract_process.py
odoo/addons/contract_api_somconnexio/services/contract_contract_service.py
odoo/addons/contract_api_somconnexio/services/contract_email_change_process.py
odoo/addons/contract_api_somconnexio/services/contract_email_change_service.py
odoo/addons/contract_api_somconnexio/services/contract_iban_change_process.py
odoo/addons/contract_api_somconnexio/services/contract_iban_change_service.py
odoo/addons/contract_api_somconnexio/services/contract_one_shot_process.py
odoo/addons/contract_api_somconnexio/services/contract_one_shot_service.py
odoo/addons/contract_api_somconnexio/services/schemas.py
odoo/addons/contract_api_somconnexio/services/contract_process/__init__.py
odoo/addons/contract_api_somconnexio/services/contract_process/adsl.py
odoo/addons/contract_api_somconnexio/services/contract_process/ba.py
odoo/addons/contract_api_somconnexio/services/contract_process/base.py
odoo/addons/contract_api_somconnexio/services/contract_process/fiber.py
odoo/addons/contract_api_somconnexio/services/contract_process/mobile.py
odoo/addons/contract_api_somconnexio/services/contract_process/router4g.py
odoo/addons/contract_api_somconnexio/services/contract_process/switchboard.py
odoo/addons/contract_api_somconnexio/tests/__init__.py
odoo/addons/contract_api_somconnexio/tests/models/__init__.py
odoo_addon_contract_api_somconnexio-16.0.1.0.6.dist-info/METADATA
odoo_addon_contract_api_somconnexio-16.0.1.0.6.dist-info/WHEEL
odoo_addon_contract_api_somconnexio-16.0.1.0.6.dist-info/top_level.txt
odoo_addon_contract_api_somconnexio-16.0.1.0.6.dist-info/RECORD
