Metadata-Version: 2.1
Name: odoo-addon-contract-api-somconnexio
Version: 16.0.1.0.6
Summary: Expose the REST API used in Som Connexió to create and manage contracts in Odoo.
Home-page: https://git.coopdevs.org/coopdevs/som-connexio/odoo/odoo-somconnexio
Author: Som Connexió SCCL, Coopdevs Treball SCCL
License: AGPL-3
Platform: UNKNOWN
Classifier: Programming Language :: Python
Classifier: Framework :: Odoo
Classifier: Framework :: Odoo :: 16.0
Classifier: License :: OSI Approved :: GNU Affero General Public License v3
Requires-Python: >=3.10
Requires-Dist: faker
Requires-Dist: odoo-addon-contract-group-somconnexio <16.1dev,>=16.0dev
Requires-Dist: odoo-addon-res-partner-api-somconnexio <16.1dev,>=16.0dev
Requires-Dist: odoo-addon-somconnexio <16.1dev,>=16.0dev
Requires-Dist: odoo-addon-switchboard-somconnexio <16.1dev,>=16.0dev
Requires-Dist: odoo <16.1dev,>=16.0a
